werkflow_jira/__init__.py
werkflow_jira/content.py
werkflow_jira/jira.py
werkflow_jira/models/__init__.py
werkflow_jira/models/requests/__init__.py
werkflow_jira/models/requests/errors/__init__.py
werkflow_jira/models/requests/errors/bad_request_error.py
werkflow_jira/models/requests/errors/method_not_allowed_error.py
werkflow_jira/models/requests/errors/resource_not_found_error.py
werkflow_jira/models/requests/errors/server_failed_error.py
werkflow_jira/models/requests/errors/unauthorized_request_error.py
werkflow_jira/models/requests/errors/unprocessable_content_error.py
werkflow_jira/models/requests/jira/__init__.py
werkflow_jira/models/requests/jira/issue.py
werkflow_jira/models/requests/jira/jira_issue.py
werkflow_jira/models/requests/jira/jira_issue_batch.py
werkflow_jira/models/requests/jira/jira_issue_link.py
werkflow_jira/models/requests/jira/content/__init__.py
werkflow_jira/models/requests/jira/content/child/__init__.py
werkflow_jira/models/requests/jira/content/child/jira_child_attrs.py
werkflow_jira/models/requests/jira/content/child/jira_child_block.py
werkflow_jira/models/requests/jira/content/inline/__init__.py
werkflow_jira/models/requests/jira/content/inline/jira_inline_attrs.py
werkflow_jira/models/requests/jira/content/inline/jira_inline_content.py
werkflow_jira/models/requests/jira/content/marks/__init__.py
werkflow_jira/models/requests/jira/content/marks/jira_content_mark.py
werkflow_jira/models/requests/jira/content/marks/jira_content_mark_attrs.py
werkflow_jira/models/requests/jira/content/top_level/__init__.py
werkflow_jira/models/requests/jira/content/top_level/jira_top_level_attrs.py
werkflow_jira/models/requests/jira/content/top_level/jira_top_level_block.py
werkflow_jira/models/responses/__init__.py
werkflow_jira/models/responses/jira/__init__.py
werkflow_jira/models/responses/jira/jira_issue_link_type.py
werkflow_jira/models/responses/jira/jira_issue_link_types.py
werkflow_jira/models/responses/jira/jira_issue_priority.py
werkflow_jira-0.3.0.dist-info/licenses/LICENSE
werkflow_jira-0.3.0.dist-info/METADATA
werkflow_jira-0.3.0.dist-info/WHEEL
werkflow_jira-0.3.0.dist-info/top_level.txt
werkflow_jira-0.3.0.dist-info/RECORD
